{"id":"25","terms":[{"value":"http://data.education.fr/voc/scolomfr/concept/difficult","label":"difficile","children":[]},{"value":"http://data.education.fr/voc/scolomfr/concept/easy","label":"facile","children":[]},{"value":"http://data.education.fr/voc/scolomfr/concept/medium","label":"moyen","children":[]},{"value":"http://data.education.fr/voc/scolomfr/concept/very_difficult","label":"très difficile","children":[]},{"value":"http://data.education.fr/voc/scolomfr/concept/very_easy","label":"très facile","children":[]}]}